{
    "line":5,
    "markers":[
        {
            "name":"จุดหอพักนิสิตหญิงสุพรรณนิการ์",
            "coordinate":{"latitude":13.852376,
            "longitude":100.580682}
        },
        {
            "name":"จุดหอแสงจันทร์",
            "coordinate":{"latitude":13.852957,
            "longitude":100.580623}
        },
        {
            "name":"จุดหอพักหญิงขจีนุช",
            "coordinate":{"latitude":13.853321,
            "longitude":100.580520}
        },
        {
            "name":"จุดหอพักKritsana",
            "coordinate":{"latitude":13.853609,
            "longitude":100.580420}
        },
        {
            "name":"จุดToo Fast To Sleep@KU",
            "coordinate":{"latitude":13.853504,
            "longitude":100.578993}
        },
        {
            "name":"จุดอาคารสวัสดิการ มก.",
            "coordinate":{"latitude":13.853138,
            "longitude":100.578402}
        },
        {
            "name":"จุดคลังยาเกษตร",
            "coordinate":{"latitude":13.852481,
            "longitude":100.576723}
        },
        {
            "name":"จุดคณะอุตสาหกรรมเกษตร",
            "coordinate":{"latitude":13.851977,
            "longitude":100.572463}
        },
        {
            "name":"จุดอาคารพุทธเกษตร",
            "coordinate":{"latitude":13.850572,
            "longitude":100.572437}
        },
        {
            "name":"จุดอาคารพืชไร่",
            "coordinate":{"latitude":13.850112,
            "longitude":100.572404}
        },
        {
            "name":"จุดสำนักหอสมุด",
            "coordinate":{"latitude":13.848146,
            "longitude":100.572430}
        },
        {
            "name":"จุดคณะวนศาสตร์",
            "coordinate":{"latitude":13.846444,
            "longitude":100.572593}
        },
        {
            "name":"จุดสำนักหอสมุด",
            "coordinate":{"latitude":13.847830,
            "longitude":100.572590}
        },
        {
            "name":"จุดคณะเกษตร",
            "coordinate":{"latitude":13.848775,
            "longitude":100.572608}
        },
        {
            "name":"จุดอาคารพุทธเกษตรฝั่งตรงข้าม",
            "coordinate":{"latitude":13.850542,
            "longitude":100.572627}
        },
        {
            "name":"จุดคณะอุตสาหกรรมเกษตร",
            "coordinate":{"latitude":13.851908,
            "longitude":100.572638}
        }
    ]
}